{
	"params": [
        {
            "name": "Events",
            "type": "DropDown('Default Cam Zoom (Global)', 'Notification (Global)', 'Popup (Global)', 'Window Name (Global)', 'Foot Kisser (Sonichu)', 'Duet (Hudson)', 'Loading Screen (Hudson)')",
            "defaultValue": ""
        },
        {
            "name": "Value 1",
            "type": "String",
            "defaultValue": ""
        },
        {
            "name": "Value 2",
            "type": "String",
            "defaultValue": ""
        }
	]
}